pymediafire
