Metadata-Version: 1.0
Name: pymediafire
Version: 0.1.3
Summary: A basic module to access MediaFire's rest API
Home-page: https://pypi.python.org
Author: Stefan Champailler
Author-email: schampailler@skynet.be
License: LICENSE.txt
Platform: UNKNOWN
Classifier: Intended Audience :: Developers
Classifier: Development Status :: 4 - Beta
Classifier: Environment :: Web Environment
Classifier: License :: OSI Approved :: GNU Lesser General Public License v3 or later (LGPLv3+)
Classifier: Programming Language :: Python :: 2.7
Classifier: Topic :: Internet
